LICENSE.md
MANIFEST.in
README.md
setup.py
admin_tabler/__init__.py
admin_tabler/admin.py
admin_tabler/apps.py
admin_tabler/forms.py
admin_tabler/urls.py
admin_tabler/utils.py
admin_tabler/views.py
admin_tabler/migrations/__init__.py
admin_tabler/static/.gitkeep
admin_tabler/static/dist/css/demo.css
admin_tabler/static/dist/css/demo.min.css
admin_tabler/static/dist/css/demo.rtl.css
admin_tabler/static/dist/css/demo.rtl.min.css
admin_tabler/static/dist/css/forms.css
admin_tabler/static/dist/css/tabler-flags.css
admin_tabler/static/dist/css/tabler-flags.min.css
admin_tabler/static/dist/css/tabler-flags.rtl.css
admin_tabler/static/dist/css/tabler-flags.rtl.min.css
admin_tabler/static/dist/css/tabler-payments.css
admin_tabler/static/dist/css/tabler-payments.min.css
admin_tabler/static/dist/css/tabler-payments.rtl.css
admin_tabler/static/dist/css/tabler-payments.rtl.min.css
admin_tabler/static/dist/css/tabler-social.css
admin_tabler/static/dist/css/tabler-social.min.css
admin_tabler/static/dist/css/tabler-social.rtl.css
admin_tabler/static/dist/css/tabler-social.rtl.min.css
admin_tabler/static/dist/css/tabler-vendors.css
admin_tabler/static/dist/css/tabler-vendors.min.css
admin_tabler/static/dist/css/tabler-vendors.rtl.css
admin_tabler/static/dist/css/tabler-vendors.rtl.min.css
admin_tabler/static/dist/css/tabler.css
admin_tabler/static/dist/css/tabler.min.css
admin_tabler/static/dist/css/tabler.rtl.css
admin_tabler/static/dist/css/tabler.rtl.min.css
admin_tabler/static/dist/css/widgets.css
admin_tabler/static/dist/img/icon-calendar.svg
admin_tabler/static/dist/img/icon-clock.svg
admin_tabler/static/dist/img/icon-unknown-alt.svg
admin_tabler/static/dist/img/icon-unknown.svg
admin_tabler/static/dist/img/search.svg
admin_tabler/static/dist/img/selector-icons.svg
admin_tabler/static/dist/img/flags/ad.svg
admin_tabler/static/dist/img/flags/ae.svg
admin_tabler/static/dist/img/flags/af.svg
admin_tabler/static/dist/img/flags/ag.svg
admin_tabler/static/dist/img/flags/ai.svg
django_admin_tabler.egg-info/PKG-INFO
django_admin_tabler.egg-info/SOURCES.txt
django_admin_tabler.egg-info/dependency_links.txt
django_admin_tabler.egg-info/not-zip-safe
django_admin_tabler.egg-info/top_level.txt
